my_package/__init__.py
tests/__init__.py
my_test_package_version_2-0.0.2.dist-info/LICENSE
my_test_package_version_2-0.0.2.dist-info/METADATA
my_test_package_version_2-0.0.2.dist-info/WHEEL
my_test_package_version_2-0.0.2.dist-info/top_level.txt
my_test_package_version_2-0.0.2.dist-info/RECORD
